pip_wheel_diff/__init__.py
pip_wheel_diff/__main__.py
pip_wheel_diff/clean.py
pip_wheel_diff/diff_tool.py
pip_wheel_diff/pip.py
pip_wheel_diff/uv.py
pip_wheel_diff-0.9.2.dist-info/METADATA
pip_wheel_diff-0.9.2.dist-info/WHEEL
pip_wheel_diff-0.9.2.dist-info/entry_points.txt
pip_wheel_diff-0.9.2.dist-info/licenses/LICENSE.txt
pip_wheel_diff-0.9.2.dist-info/RECORD
