Metadata-Version: 2.3
Name: pip-wheel-diff
Version: 0.9.2
Summary: Download or build two wheels and launch a diff tool to compare them
Project-URL: Documentation, https://github.com/sbidoul/pip-wheel-diff#readme
Project-URL: Issues, https://github.com/sbidoul/pip-wheel-diff/issues
Project-URL: Source, https://github.com/sbidoul/pip-wheel-diff
Author-email: Stéphane Bidoul <stephane.bidoul@gmail.com>
License-Expression: MIT
License-File: LICENSE.txt
Classifier: Development Status :: 4 - Beta
Classifier: Programming Language :: Python
Classifier: Programming Language :: Python :: 3.7
Classifier: Programming Language :: Python :: 3.8
Classifier: Programming Language :: Python :: 3.9
Classifier: Programming Language :: Python :: 3.10
Classifier: Programming Language :: Python :: 3.11
Classifier: Programming Language :: Python :: 3.12
Classifier: Programming Language :: Python :: Implementation :: CPython
Classifier: Programming Language :: Python :: Implementation :: PyPy
Requires-Python: >=3.7
